MANIFEST.in
README.rst
setup.py
alf/__init__.py
alf/adapters.py
alf/auth.py
alf/client.py
alf/managers.py
alf/tokens.py
alf.egg-info/PKG-INFO
alf.egg-info/SOURCES.txt
alf.egg-info/dependency_links.txt
alf.egg-info/requires.txt
alf.egg-info/top_level.txt
tests/adapters/__init__.py
tests/adapters/test_mount_retry_adapter.py
tests/auth/__init__.py
tests/auth/test_auth.py
tests/client/__init__.py
tests/client/test_client.py
tests/managers/__init__.py
tests/managers/test_token_manager.py
tests/tokens/__init__.py
tests/tokens/test_token.py