Metadata-Version: 1.1
Name: alf
Version: 0.7.1
Summary: OAuth Client
Home-page: https://github.com/globocom/alf
Author: Globo.com
Author-email: timecore@corp.globo.com
License: MIT
Keywords: oauth client client_credentials requests
Platform: UNKNOWN
Classifier: Intended Audience :: Developers
Classifier: License :: OSI Approved :: MIT License
Classifier: Programming Language :: Python :: 2.7
Classifier: Programming Language :: Python :: 3
Classifier: Programming Language :: Python :: 3.3
